pelican/plugins/nginx_alias_map/__init__.py
pelican/plugins/nginx_alias_map/nginx_alias_map.py
pelican/plugins/nginx_alias_map/test_data/alias_map.expected
pelican/plugins/nginx_alias_map/test_data/test_no_alias.md
pelican/plugins/nginx_alias_map/test_data/test_one_alias.md
pelican/plugins/nginx_alias_map/test_data/test_two_alias.md
pelican/plugins/nginx_alias_map/test_nginx_alias_map.py
pelican_nginx_alias_map-2.0.6.dist-info/METADATA
pelican_nginx_alias_map-2.0.6.dist-info/WHEEL
pelican_nginx_alias_map-2.0.6.dist-info/licenses/LICENSE.txt
pelican_nginx_alias_map-2.0.6.dist-info/RECORD
