Metadata-Version: 2.4
Name: pelican-nginx-alias-map
Version: 2.0.6
Summary: This Pelican plugin creates an nginx-compatible map between the final page locations and prior locations, defined in the `Alias` attribute for any article or page.
License: MIT
License-File: LICENSE.txt
Keywords: pelican,plugin
Author: Gaige B. Paulsen
Author-email: gaige@cluetrust.com
Requires-Python: >=3.9,<4.0
Classifier: Development Status :: 5 - Production/Stable
Classifier: Environment :: Plugins
Classifier: Framework :: Pelican
Classifier: Framework :: Pelican :: Plugins
Classifier: Intended Audience :: End Users/Desktop
Classifier: License :: OSI Approved :: MIT License
Classifier: Operating System :: OS Independent
Classifier: Programming Language :: Python :: 3
Classifier: Programming Language :: Python :: 3.9
Classifier: Programming Language :: Python :: 3.10
Classifier: Programming Language :: Python :: 3.11
Classifier: Programming Language :: Python :: 3.12
Classifier: Programming Language :: Python :: 3.13
Classifier: Programming Language :: Python :: 3.14
Classifier: Topic :: Internet :: WWW/HTTP
Classifier: Topic :: Software Development :: Libraries :: Python Modules
Provides-Extra: markdown
Requires-Dist: markdown (>=3.2,!=3.3.5) ; extra == "markdown"
Requires-Dist: pelican (>=4.5)
Project-URL: Documentation, https://docs.getpelican.com
Project-URL: Issue Tracker, https://github.com/gaige/nginx_alias_map/issues
Project-URL: Repository, https://github.com/gaige/nginx_alias_map
